flask_keen.py
setup.py
Flask_Keen.egg-info/PKG-INFO
Flask_Keen.egg-info/SOURCES.txt
Flask_Keen.egg-info/dependency_links.txt
Flask_Keen.egg-info/requires.txt
Flask_Keen.egg-info/top_level.txt