Metadata-Version: 1.0
Name: Flask-Keen
Version: 0.1.0
Summary: Flask-Keen
Home-page: https://github.com/raicheff/flask-keen
Author: Boris Raicheff
Author-email: b@raicheff.com
License: UNKNOWN
Platform: UNKNOWN
